tidyexp/__init__.py
tidyexp/load/__init__.py
tidyexp/load/load_log.py
tidyexp/load/load_model.py
tidyexp/save/__init__.py
tidyexp/save/model_log.py
tidyexp/save/stat_log.py
tidyexp/save/stat_log_test.py
tidyexp/tidyexp.py
tidyexp/tidyexp_test.py
tidyexp/utils/__init__.py
tidyexp/utils/helpers.py
tidyexp-0.1.0.dist-info/LICENSE
tidyexp-0.1.0.dist-info/WHEEL
tidyexp-0.1.0.dist-info/METADATA
tidyexp-0.1.0.dist-info/RECORD
