Metadata-Version: 2.1
Name: tidyexp
Version: 0.1.0
Summary: Easy-to-use, offline-first ML experiment management solution.
License: MIT
Author: TidyExp Team
Author-email: 500076406@stu.upes.ac.in
Requires-Python: >=3.7,<4.0
Classifier: License :: OSI Approved :: MIT License
Classifier: Programming Language :: Python :: 3
Classifier: Programming Language :: Python :: 3.10
Classifier: Programming Language :: Python :: 3.7
Classifier: Programming Language :: Python :: 3.8
Classifier: Programming Language :: Python :: 3.9
Requires-Dist: google-api-core (==2.7.1)
Requires-Dist: google-api-python-client (==2.43.0)
Requires-Dist: google-auth (==2.6.2)
Requires-Dist: google-auth-httplib2 (==0.1.0)
Requires-Dist: google-auth-oauthlib (>=0.5.1,<0.6.0)
Requires-Dist: googleapis-common-protos (==1.56.0)
Requires-Dist: h5py (==3.6.0)
Requires-Dist: pygit2 (==1.9.1)
Requires-Dist: pytest (>=7.1.2,<8.0.0)
Requires-Dist: rich (>=12.2.0,<13.0.0)
